{
  "designcatalogue" :
  [
    {
      "name": "MandirDesign-1",
      "dimensionsx" : 900,
      "dimensionsy" : 1200,
      "size": "4ft x 3ft",
      "supplier": "LightYear",
      "construction": "Standalone",
      "designelement": 
      [
        {
          "dxfurl": "dxf/Mandir Jali Objects/23.dxf",
          "thumbnailurl": "dxf/Mandir Jali Objects/23.jpg",
          "positionx": 0,
          "positiony": 0,
          "rotation": 0,
          "scale": 1.5
        },
        {
          "dxfurl": "dxf/Mandir Jali Objects/10.dxf",
          "thumbnailurl": "dxf/Mandir Jali Objects/10.jpg",
          "positionx": -300,
          "positiony": 350,
          "rotation": 0,
          "scale": 1.5
        },
        {
          "dxfurl": "dxf/Mandir Jali Objects/10.dxf",
          "thumbnailurl": "dxf/Mandir Jali Objects/10.jpg",
          "positionx": 300,
          "positiony": 350,
          "rotation": 0,
          "scale": 1.5
        },
        {
          "dxfurl": "dxf/Mandir Jali Objects/5.dxf",
          "thumbnailurl": "dxf/Mandir Jali Objects/5.jpg",
          "positionx": -300,
          "positiony": -400,
          "rotation": 0,
          "scale": 1.5
        },
        {
          "dxfurl": "dxf/Mandir Jali Objects/5.dxf",
          "thumbnailurl": "dxf/Mandir Jali Objects/5.jpg",
          "positionx": 300,
          "positiony": -400,
          "rotation": 0,
          "scale": 1.5
        }
      ]
    },
    {
      "name": "MandirDesign-2",
      "dimensionsx" : 900,
      "dimensionsy" : 1200,
      "size": "4ft x 3ft",
      "supplier": "LightYear",
      "construction": "Standalone",
      "designelement": 
      [
        {
          "dxfurl": "dxf/Mandir Jali Objects/23.dxf",
          "thumbnailurl": "dxf/Mandir Jali Objects/23.jpg",
          "positionx": 0,
          "positiony": 0,
          "rotation": 0,
          "scale": 1.5
        },
        {
          "dxfurl": "dxf/Mandir Jali Objects/10.dxf",
          "thumbnailurl": "dxf/Mandir Jali Objects/10.jpg",
          "positionx": -300,
          "positiony": 350,
          "rotation": 0,
          "scale": 1.5
        },
        {
          "dxfurl": "dxf/Mandir Jali Objects/10.dxf",
          "thumbnailurl": "dxf/Mandir Jali Objects/10.jpg",
          "positionx": 300,
          "positiony": 350,
          "rotation": 0,
          "scale": 1.5
        },
        {
          "dxfurl": "dxf/Mandir Jali Objects/5.dxf",
          "thumbnailurl": "dxf/Mandir Jali Objects/5.jpg",
          "positionx": -300,
          "positiony": -400,
          "rotation": 0,
          "scale": 1.5
        },
        {
          "dxfurl": "dxf/Mandir Jali Objects/5.dxf",
          "thumbnailurl": "dxf/Mandir Jali Objects/5.jpg",
          "positionx": 300,
          "positiony": -400,
          "rotation": 0,
          "scale": 1.5
        }
      ]
    }
  ]
}
